nbsmoke/.version
nbsmoke/__init__.py
nbsmoke/verify.py
nbsmoke/lint/__init__.py
nbsmoke/lint/_pyflakes.py
nbsmoke/lint/magics/__init__.py
nbsmoke/lint/magics/builtins_support.py
nbsmoke/lint/magics/holoviews_support.py
nbsmoke/tests/__init__.py
nbsmoke/tests/test_lint.py
nbsmoke/tests/test_lint_magics.py
nbsmoke/tests/test_lint_magics_hv.py
nbsmoke/tests/test_nbsmoke.py
nbsmoke/tests/test_run.py
nbsmoke/tests/test_verify.py
nbsmoke-0.6.0.dist-info/LICENSE
nbsmoke-0.6.0.dist-info/METADATA
nbsmoke-0.6.0.dist-info/WHEEL
nbsmoke-0.6.0.dist-info/entry_points.txt
nbsmoke-0.6.0.dist-info/top_level.txt
nbsmoke-0.6.0.dist-info/RECORD
