Metadata-Version: 2.1
Name: nbsmoke
Version: 0.6.0
Summary: Basic notebook checks. Do they run? Do they contain lint?
Home-page: https://github.com/pyviz-dev/nbsmoke
Author: pyviz contributors
Author-email: dev@pyviz.org
License: BSD-3
Platform: UNKNOWN
Classifier: Development Status :: 5 - Production/Stable
Classifier: Framework :: Pytest
Classifier: Intended Audience :: Developers
Classifier: Topic :: Software Development :: Testing
Classifier: Programming Language :: Python
Classifier: Programming Language :: Python :: 3
Classifier: Operating System :: OS Independent
Classifier: License :: OSI Approved :: BSD License
Requires-Python: >=3.4
License-File: LICENSE
Requires-Dist: param (>=1.7.0)
Requires-Dist: pytest (>=3.1.1)
Requires-Dist: pyflakes
Requires-Dist: jupyter-client
Requires-Dist: nbformat
Requires-Dist: nbconvert
Requires-Dist: ipykernel
Provides-Extra: all
Requires-Dist: beautifulsoup4 ; extra == 'all'
Requires-Dist: coverage ; extra == 'all'
Requires-Dist: flake8 ; extra == 'all'
Requires-Dist: holoviews ; extra == 'all'
Requires-Dist: keyring ; extra == 'all'
Requires-Dist: param (>=1.7.0) ; extra == 'all'
Requires-Dist: pyct (>=0.4.4) ; extra == 'all'
Requires-Dist: requests ; extra == 'all'
Requires-Dist: rfc3986 ; extra == 'all'
Requires-Dist: setuptools (>=30.3.0) ; extra == 'all'
Requires-Dist: twine ; extra == 'all'
Provides-Extra: build
Requires-Dist: param (>=1.7.0) ; extra == 'build'
Requires-Dist: pyct (>=0.4.4) ; extra == 'build'
Requires-Dist: setuptools (>=30.3.0) ; extra == 'build'
Provides-Extra: holoviews-magics
Requires-Dist: holoviews ; extra == 'holoviews-magics'
Provides-Extra: lint
Requires-Dist: flake8 ; extra == 'lint'
Provides-Extra: tests
Requires-Dist: coverage ; extra == 'tests'
Requires-Dist: twine ; extra == 'tests'
Requires-Dist: rfc3986 ; extra == 'tests'
Requires-Dist: keyring ; extra == 'tests'
Requires-Dist: flake8 ; extra == 'tests'
Requires-Dist: holoviews ; extra == 'tests'
Requires-Dist: requests ; extra == 'tests'
Requires-Dist: beautifulsoup4 ; extra == 'tests'
Provides-Extra: verify
Requires-Dist: requests ; extra == 'verify'
Requires-Dist: beautifulsoup4 ; extra == 'verify'
